Metadata-Version: 2.1
Name: cloudconnect
Version: 0.0.2
Summary: Traing Machine learing models in the cloud
Home-page: UNKNOWN
Author: Ahmed Ibrahim
Author-email: ahmedibarhim556@gmail.com
License: MIT
Keywords: machine learning,deep learning
Platform: UNKNOWN
Classifier: Development Status :: 5 - Production/Stable
Classifier: Intended Audience :: Education
Classifier: Operating System :: Microsoft :: Windows :: Windows 10
Classifier: License :: OSI Approved :: MIT License
Classifier: Programming Language :: Python :: 3
License-File: LICENCE.txt
